Metadata-Version: 2.1
Name: pyproc2
Version: 1.2.2
Summary: Python library for reading data from UNIX /proc/ directory
Home-page: http://pypi.org/project/pyproc2
Author: Adam Jenca
Author-email: jenca.adam@gmail.com
License: UNKNOWN
Platform: UNKNOWN
Classifier: Development Status :: 3 - Alpha
Classifier: Environment :: Console
Classifier: License :: OSI Approved :: GNU General Public License (GPL)
Classifier: Operating System :: POSIX :: Linux
Classifier: Programming Language :: Python :: 3
Classifier: Topic :: System
License-File: LICENSE
